Workbook
Name price: 汇总!$C$3
Name price_zl: ZL昆州农场!$B$4
Name 价格: DM新州老农场!$B$5
Name 每倾费用: ZL昆州农场!$B$5
Name 种植面积_H: ZL昆州农场!$B$2

Sheet 汇总
B3: 坚果收购价 | C3: 4.2
D5: 2027 | F5: 2028 | H5: 2029 | J5: 2030
B6: 资产价格待评估 | D6: 产量 | E6: 利润 | F6: 产量 | G6: 利润 | H6: 产量 | I6: 利润 | J6: 产量 | K6: 利润
B7: 2200 | C7: ZL昆州 | D7: =ZL昆州农场!D6 -> 600 | E7: =ZL昆州农场!D9 -> 985000 | F7: =ZL昆州农场!E6 -> 800 | G7: =ZL昆州农场!E9 -> 2105000 | H7: =ZL昆州农场!F6 -> 800 | I7: =ZL昆州农场!F9 -> 2105000 | J7: =ZL昆州农场!G6 -> 800 | K7: =ZL昆州农场!G9 -> 2105000 | L7: 优质资产
B8: 2200 | C8: DM新州 | D8: =DM新州老农场!D7 -> 550 | E8: =DM新州老农场!D10 -> 15000 | F8: =DM新州老农场!E7 -> 675 | G8: =DM新州老农场!E10 -> 420000 | H8: =DM新州老农场!F7 -> 825 | I8: =DM新州老农场!F10 -> 750000 | J8: =DM新州老农场!G7 -> 825 | K8: =DM新州老农场!G10 -> 450000 | L8: 问题资产，1-2年内争取处置2个农场收回800-1000万资金
B9: 500 | C9: 加工厂 | D9: =SUM(D7:D8) -> 1150 | E9: 1000000 | F9: 1500 | G9: 1900000 | H9: 1500 | I9: 1900000 | J9: 1500 | K9: 1900000 | L9: 优质资产
B10: =SUM(B7:B9) -> 4900 | E10: =SUM(E7:E9) -> 2000000 | G10: =SUM(G7:G9) -> 4425000 | I10: =SUM(I7:I9) -> 4755000 | K10: =SUM(K7:K9) -> 4455000

Sheet ZL昆州农场
B1: 种植面积（H） | C1: 土地面积（H） | D1: 可新种植面积（H）
B2: 190 | C2: 420 | D2: 90 | G2: 没有计算新买100公顷种植的投入及产出
A3: 平均出仁率 | B3: 0.44
A4: 价格 | B4: =汇总!C3+(44-33)/33*汇总!C3 -> 5.6
A5: 每倾费用 | B5: 12500 | D5: 2027 | E5: 2028 | F5: 2029 | G5: 2030 | H5: 2031
C6: 产量 | D6: 600 | E6: 800 | F6: 800 | G6: 800 | H6: 800
C7: 收入 | D7: =D6*price_zl*1000 -> 3360000 | E7: =E6*price_zl*1000 -> 4480000 | F7: =F6*price_zl*1000 -> 4480000 | G7: =G6*price_zl*1000 -> 4480000 | H7: =H6*price_zl*1000 -> 4480000
C8: 费用 | D8: =每倾费用*种植面积_H -> 2375000 | E8: =每倾费用*种植面积_H -> 2375000 | F8: =每倾费用*种植面积_H -> 2375000 | G8: =每倾费用*种植面积_H -> 2375000 | H8: =每倾费用*种植面积_H -> 2375000
C9: 利润 | D9: =D7-D8 -> 985000 | E9: =E7-E8 -> 2105000 | F9: =F7-F8 -> 2105000 | G9: =G7-G8 -> 2105000 | H9: =H7-H8 -> 2105000

Sheet DM新州老农场
B2: 种植面积（H） | C2: 土地面积（H） | D2: 可新种植面积（H） | G2: 问题资产，1-2年内争取处置2个农场收回800-1000万资金，另LDR1有Rezoning的可能性
B3: 290 | C3: 490 | D3: 0
A4: 平均出仁率 | B4: 0.33
A5: 价格 | B5: =price -> 4.2
D6: 2027 | E6: 2028 | F6: 2029 | G6: 2030
C7: 产量 | D7: 550 | E7: 675 | F7: 825 | G7: 825 | H7: 数据来源于 管理方
C8: 收入
C9: 费用
C10: 利润 | D10: 15000 | E10: 420000 | F10: 750000 | G10: 450000
